{
    "RECORDS": [
        {
            "id": "85ffa8ee-3a36-47f0-9cb3-cab09dd27571",
            "code": "WHOLESALE",
            "name_kh": "លក់ដុំ",
            "name_en": "Wholesale",
            "created_at": "2/1/2022 10:48:42",
            "updated_at": "2/1/2022 10:48:42",
            "deleted_at": ""
        },
        {
            "id": "85ffa8ee-3a36-47f0-9cb3-cab09dd27572",
            "code": "STATIONSALE",
            "name_kh": "ស្ថានីយ៍",
            "name_en": "Station",
            "created_at": "",
            "updated_at": "",
            "deleted_at": ""
        }
    ]
}