{
    "RECORDS": [
        {
            "id": "URL001",
            "method": "GET",
            "uri": "/",
            "route_name": "dashboard",
            "acitve": "1",
            "is_menu": "1",
            "created_at": "2022-5-18 05:04:00",
            "updated_at": "2022-5-18 05:04:00",
            "deleted_at": ""
        },
        {
            "id": "URL002",
            "method": "GET",
            "uri": "address/{type}/{id}",
            "route_name": "address",
            "acitve": "1",
            "is_menu": "0",
            "created_at": "2022-5-18 05:04:00",
            "updated_at": "2022-5-18 05:04:00",
            "deleted_at": ""
        },
        {
            "id": "URL003",
            "method": "GET",
            "uri": "dashboard/print",
            "route_name": "dashboard.print",
            "acitve": "1",
            "is_menu": "0",
            "created_at": "2022-5-18 05:04:00",
            "updated_at": "2022-5-18 05:04:00",
            "deleted_at": ""
        },
        {
            "id": "URL004",
            "method": "GET",
            "uri": "expense/item",
            "route_name": "expense.item.index",
            "acitve": "1",
            "is_menu": "0",
            "created_at": "2022-5-18 05:04:00",
            "updated_at": "2022-5-18 05:04:00",
            "deleted_at": ""
        },
        {
            "id": "URL005",
            "method": "POST",
            "uri": "expense/item",
            "route_name": "expense.item.store",
            "acitve": "1",
            "is_menu": "0",
            "created_at": "2022-5-18 05:04:00",
            "updated_at": "2022-5-18 05:04:00",
            "deleted_at": ""
        },
        {
            "id": "URL006",
            "method": "GET",
            "uri": "expense/item/create",
            "route_name": "expense.item.create",
            "acitve": "1",
            "is_menu": "0",
            "created_at": "2022-5-18 05:04:00",
            "updated_at": "2022-5-18 05:04:00",
            "deleted_at": ""
        },
        {
            "id": "URL007",
            "method": "PATCH",
            "uri": "expense/item/{id}",
            "route_name": "expense.item.update",
            "acitve": "1",
            "is_menu": "0",
            "created_at": "2022-5-18 05:04:00",
            "updated_at": "2022-5-18 05:04:00",
            "deleted_at": ""
        },
        {
            "id": "URL008",
            "method": "GET",
            "uri": "expense/item/{id}",
            "route_name": "expense.item.show",
            "acitve": "1",
            "is_menu": "0",
            "created_at": "2022-5-18 05:04:00",
            "updated_at": "2022-5-18 05:04:00",
            "deleted_at": ""
        },
        {
            "id": "URL009",
            "method": "DELETE",
            "uri": "expense/item/{id}",
            "route_name": "expense.item.destroy",
            "acitve": "1",
            "is_menu": "0",
            "created_at": "2022-5-18 05:04:00",
            "updated_at": "2022-5-18 05:04:00",
            "deleted_at": ""
        },
        {
            "id": "URL010",
            "method": "GET",
            "uri": "expense/item/{id}/edit",
            "route_name": "expense.item.edit",
            "acitve": "1",
            "is_menu": "0",
            "created_at": "2022-5-18 05:04:00",
            "updated_at": "2022-5-18 05:04:00",
            "deleted_at": ""
        },
        {
            "id": "URL011",
            "method": "POST",
            "uri": "loan/daily",
            "route_name": "loan.daily.store",
            "acitve": "1",
            "is_menu": "0",
            "created_at": "2022-5-18 05:04:00",
            "updated_at": "2022-5-18 05:04:00",
            "deleted_at": ""
        },
        {
            "id": "URL012",
            "method": "GET",
            "uri": "loan/daily/create",
            "route_name": "loan.daily.create",
            "acitve": "1",
            "is_menu": "0",
            "created_at": "2022-5-18 05:04:00",
            "updated_at": "2022-5-18 05:04:00",
            "deleted_at": ""
        },
        {
            "id": "URL013",
            "method": "PATCH",
            "uri": "loan/daily/{id}",
            "route_name": "loan.daily.update",
            "acitve": "1",
            "is_menu": "0",
            "created_at": "2022-5-18 05:04:00",
            "updated_at": "2022-5-18 05:04:00",
            "deleted_at": ""
        },
        {
            "id": "URL014",
            "method": "GET",
            "uri": "loan/daily/{id}/edit",
            "route_name": "loan.daily.edit",
            "acitve": "1",
            "is_menu": "0",
            "created_at": "2022-5-18 05:04:00",
            "updated_at": "2022-5-18 05:04:00",
            "deleted_at": ""
        },
        {
            "id": "URL015",
            "method": "GET",
            "uri": "loan/download",
            "route_name": "operation.loan.request.download",
            "acitve": "1",
            "is_menu": "0",
            "created_at": "2022-5-18 05:04:00",
            "updated_at": "2022-5-18 05:04:00",
            "deleted_at": ""
        },
        {
            "id": "URL016",
            "method": "GET",
            "uri": "loan/export",
            "route_name": "loan.export",
            "acitve": "1",
            "is_menu": "0",
            "created_at": "2022-5-18 05:04:00",
            "updated_at": "2022-5-18 05:04:00",
            "deleted_at": ""
        },
        {
            "id": "URL017",
            "method": "POST",
            "uri": "loan/half-monthly",
            "route_name": "loan.half-monthly.store",
            "acitve": "1",
            "is_menu": "0",
            "created_at": "2022-5-18 05:04:00",
            "updated_at": "2022-5-18 05:04:00",
            "deleted_at": ""
        },
        {
            "id": "URL018",
            "method": "GET",
            "uri": "loan/half-monthly/create",
            "route_name": "loan.half-monthly.create",
            "acitve": "1",
            "is_menu": "0",
            "created_at": "2022-5-18 05:04:00",
            "updated_at": "2022-5-18 05:04:00",
            "deleted_at": ""
        },
        {
            "id": "URL019",
            "method": "PATCH",
            "uri": "loan/half-monthly/{id}",
            "route_name": "loan.half-monthly.update",
            "acitve": "1",
            "is_menu": "0",
            "created_at": "2022-5-18 05:04:00",
            "updated_at": "2022-5-18 05:04:00",
            "deleted_at": ""
        },
        {
            "id": "URL020",
            "method": "GET",
            "uri": "loan/half-monthly/{id}/edit",
            "route_name": "loan.half-monthly.edit",
            "acitve": "1",
            "is_menu": "0",
            "created_at": "2022-5-18 05:04:00",
            "updated_at": "2022-5-18 05:04:00",
            "deleted_at": ""
        },
        {
            "id": "URL021",
            "method": "GET",
            "uri": "loan/list",
            "route_name": "operation.loan.request.index",
            "acitve": "1",
            "is_menu": "0",
            "created_at": "2022-5-18 05:04:00",
            "updated_at": "2022-5-18 05:04:00",
            "deleted_at": ""
        },
        {
            "id": "URL022",
            "method": "PATCH",
            "uri": "loan/list/{id}",
            "route_name": "operation.loan.request.index.update",
            "acitve": "1",
            "is_menu": "0",
            "created_at": "2022-5-18 05:04:00",
            "updated_at": "2022-5-18 05:04:00",
            "deleted_at": ""
        },
        {
            "id": "URL023",
            "method": "GET",
            "uri": "loan/list/{id}",
            "route_name": "operation.loan.request.index.show",
            "acitve": "1",
            "is_menu": "0",
            "created_at": "2022-5-18 05:04:00",
            "updated_at": "2022-5-18 05:04:00",
            "deleted_at": ""
        },
        {
            "id": "URL024",
            "method": "DELETE",
            "uri": "loan/list/{id}",
            "route_name": "operation.loan.request.index.destroy",
            "acitve": "1",
            "is_menu": "0",
            "created_at": "2022-5-18 05:04:00",
            "updated_at": "2022-5-18 05:04:00",
            "deleted_at": ""
        },
        {
            "id": "URL025",
            "method": "GET",
            "uri": "loan/list/{id}/edit",
            "route_name": "operation.loan.request.index.edit",
            "acitve": "1",
            "is_menu": "0",
            "created_at": "2022-5-18 05:04:00",
            "updated_at": "2022-5-18 05:04:00",
            "deleted_at": ""
        },
        {
            "id": "URL026",
            "method": "POST",
            "uri": "loan/twice-weekly",
            "route_name": "loan.twice-weekly.store",
            "acitve": "1",
            "is_menu": "0",
            "created_at": "2022-5-18 05:04:00",
            "updated_at": "2022-5-18 05:04:00",
            "deleted_at": ""
        },
        {
            "id": "URL027",
            "method": "GET",
            "uri": "loan/twice-weekly/create",
            "route_name": "loan.twice-weekly.create",
            "acitve": "1",
            "is_menu": "0",
            "created_at": "2022-5-18 05:04:00",
            "updated_at": "2022-5-18 05:04:00",
            "deleted_at": ""
        },
        {
            "id": "URL028",
            "method": "PATCH",
            "uri": "loan/twice-weekly/{id}",
            "route_name": "loan.twice-weekly.update",
            "acitve": "1",
            "is_menu": "0",
            "created_at": "2022-5-18 05:04:00",
            "updated_at": "2022-5-18 05:04:00",
            "deleted_at": ""
        },
        {
            "id": "URL029",
            "method": "GET",
            "uri": "loan/twice-weekly/{id}/edit",
            "route_name": "loan.twice-weekly.edit",
            "acitve": "1",
            "is_menu": "0",
            "created_at": "2022-5-18 05:04:00",
            "updated_at": "2022-5-18 05:04:00",
            "deleted_at": ""
        },
        {
            "id": "URL030",
            "method": "POST",
            "uri": "loan/weekly",
            "route_name": "loan.weekly.store",
            "acitve": "1",
            "is_menu": "0",
            "created_at": "2022-5-18 05:04:00",
            "updated_at": "2022-5-18 05:04:00",
            "deleted_at": ""
        },
        {
            "id": "URL031",
            "method": "GET",
            "uri": "loan/weekly/create",
            "route_name": "loan.weekly.create",
            "acitve": "1",
            "is_menu": "0",
            "created_at": "2022-5-18 05:04:00",
            "updated_at": "2022-5-18 05:04:00",
            "deleted_at": ""
        },
        {
            "id": "URL032",
            "method": "PATCH",
            "uri": "loan/weekly/{id}",
            "route_name": "loan.weekly.update",
            "acitve": "1",
            "is_menu": "0",
            "created_at": "2022-5-18 05:04:00",
            "updated_at": "2022-5-18 05:04:00",
            "deleted_at": ""
        },
        {
            "id": "URL033",
            "method": "GET",
            "uri": "loan/weekly/{id}/edit",
            "route_name": "loan.weekly.edit",
            "acitve": "1",
            "is_menu": "0",
            "created_at": "2022-5-18 05:04:00",
            "updated_at": "2022-5-18 05:04:00",
            "deleted_at": ""
        },
        {
            "id": "URL034",
            "method": "POST",
            "uri": "master-data/branch",
            "route_name": "master-data.branch.store",
            "acitve": "1",
            "is_menu": "0",
            "created_at": "2022-5-18 05:04:00",
            "updated_at": "2022-5-18 05:04:00",
            "deleted_at": ""
        },
        {
            "id": "URL035",
            "method": "GET",
            "uri": "master-data/branch",
            "route_name": "master-data.branch.index",
            "acitve": "1",
            "is_menu": "0",
            "created_at": "2022-5-18 05:04:00",
            "updated_at": "2022-5-18 05:04:00",
            "deleted_at": ""
        },
        {
            "id": "URL036",
            "method": "GET",
            "uri": "master-data/branch/create",
            "route_name": "master-data.branch.create",
            "acitve": "1",
            "is_menu": "0",
            "created_at": "2022-5-18 05:04:00",
            "updated_at": "2022-5-18 05:04:00",
            "deleted_at": ""
        },
        {
            "id": "URL037",
            "method": "DELETE",
            "uri": "master-data/branch/{id}",
            "route_name": "master-data.branch.destroy",
            "acitve": "1",
            "is_menu": "0",
            "created_at": "2022-5-18 05:04:00",
            "updated_at": "2022-5-18 05:04:00",
            "deleted_at": ""
        },
        {
            "id": "URL038",
            "method": "GET",
            "uri": "master-data/branch/{id}",
            "route_name": "master-data.branch.show",
            "acitve": "1",
            "is_menu": "0",
            "created_at": "2022-5-18 05:04:00",
            "updated_at": "2022-5-18 05:04:00",
            "deleted_at": ""
        },
        {
            "id": "URL039",
            "method": "PATCH",
            "uri": "master-data/branch/{id}",
            "route_name": "master-data.branch.update",
            "acitve": "1",
            "is_menu": "0",
            "created_at": "2022-5-18 05:04:00",
            "updated_at": "2022-5-18 05:04:00",
            "deleted_at": ""
        },
        {
            "id": "URL040",
            "method": "GET",
            "uri": "master-data/branch/{id}/edit",
            "route_name": "master-data.branch.edit",
            "acitve": "1",
            "is_menu": "0",
            "created_at": "2022-5-18 05:04:00",
            "updated_at": "2022-5-18 05:04:00",
            "deleted_at": ""
        },
        {
            "id": "URL041",
            "method": "GET",
            "uri": "master-data/deposit",
            "route_name": "master-data.deposit.index",
            "acitve": "1",
            "is_menu": "0",
            "created_at": "2022-5-18 05:04:00",
            "updated_at": "2022-5-18 05:04:00",
            "deleted_at": ""
        },
        {
            "id": "URL042",
            "method": "POST",
            "uri": "master-data/deposit",
            "route_name": "master-data.operation.deposit.request.store",
            "acitve": "1",
            "is_menu": "0",
            "created_at": "2022-5-18 05:04:00",
            "updated_at": "2022-5-18 05:04:00",
            "deleted_at": ""
        },
        {
            "id": "URL043",
            "method": "GET",
            "uri": "master-data/deposit/create",
            "route_name": "master-data.operation.deposit.request.create",
            "acitve": "1",
            "is_menu": "0",
            "created_at": "2022-5-18 05:04:00",
            "updated_at": "2022-5-18 05:04:00",
            "deleted_at": ""
        },
        {
            "id": "URL044",
            "method": "DELETE",
            "uri": "master-data/deposit/{id}",
            "route_name": "master-data.deposit.destroy",
            "acitve": "1",
            "is_menu": "0",
            "created_at": "2022-5-18 05:04:00",
            "updated_at": "2022-5-18 05:04:00",
            "deleted_at": ""
        },
        {
            "id": "URL045",
            "method": "PATCH",
            "uri": "master-data/deposit/{id}",
            "route_name": "master-data.operation.deposit.request.update",
            "acitve": "1",
            "is_menu": "0",
            "created_at": "2022-5-18 05:04:00",
            "updated_at": "2022-5-18 05:04:00",
            "deleted_at": ""
        },
        {
            "id": "URL046",
            "method": "GET",
            "uri": "master-data/deposit/{id}",
            "route_name": "master-data.operation.deposit.request.show",
            "acitve": "1",
            "is_menu": "0",
            "created_at": "2022-5-18 05:04:00",
            "updated_at": "2022-5-18 05:04:00",
            "deleted_at": ""
        },
        {
            "id": "URL047",
            "method": "GET",
            "uri": "master-data/deposit/{id}/edit",
            "route_name": "master-data.operation.deposit.request.edit",
            "acitve": "1",
            "is_menu": "0",
            "created_at": "2022-5-18 05:04:00",
            "updated_at": "2022-5-18 05:04:00",
            "deleted_at": ""
        },
        {
            "id": "URL048",
            "method": "POST",
            "uri": "master-data/expense-type",
            "route_name": "master-data.expense-type.store",
            "acitve": "1",
            "is_menu": "0",
            "created_at": "2022-5-18 05:04:00",
            "updated_at": "2022-5-18 05:04:00",
            "deleted_at": ""
        },
        {
            "id": "URL049",
            "method": "GET",
            "uri": "master-data/expense-type",
            "route_name": "master-data.expense-type.index",
            "acitve": "1",
            "is_menu": "0",
            "created_at": "2022-5-18 05:04:00",
            "updated_at": "2022-5-18 05:04:00",
            "deleted_at": ""
        },
        {
            "id": "URL050",
            "method": "GET",
            "uri": "master-data/expense-type/create",
            "route_name": "master-data.expense-type.create",
            "acitve": "1",
            "is_menu": "0",
            "created_at": "2022-5-18 05:04:00",
            "updated_at": "2022-5-18 05:04:00",
            "deleted_at": ""
        },
        {
            "id": "URL051",
            "method": "PATCH",
            "uri": "master-data/expense-type/{id}",
            "route_name": "master-data.expense-type.update",
            "acitve": "1",
            "is_menu": "0",
            "created_at": "2022-5-18 05:04:00",
            "updated_at": "2022-5-18 05:04:00",
            "deleted_at": ""
        },
        {
            "id": "URL052",
            "method": "DELETE",
            "uri": "master-data/expense-type/{id}",
            "route_name": "master-data.expense-type.destroy",
            "acitve": "1",
            "is_menu": "0",
            "created_at": "2022-5-18 05:04:00",
            "updated_at": "2022-5-18 05:04:00",
            "deleted_at": ""
        },
        {
            "id": "URL053",
            "method": "GET",
            "uri": "master-data/expense-type/{id}",
            "route_name": "master-data.expense-type.show",
            "acitve": "1",
            "is_menu": "0",
            "created_at": "2022-5-18 05:04:00",
            "updated_at": "2022-5-18 05:04:00",
            "deleted_at": ""
        },
        {
            "id": "URL054",
            "method": "GET",
            "uri": "master-data/expense-type/{id}/edit",
            "route_name": "master-data.expense-type.edit",
            "acitve": "1",
            "is_menu": "0",
            "created_at": "2022-5-18 05:04:00",
            "updated_at": "2022-5-18 05:04:00",
            "deleted_at": ""
        },
        {
            "id": "URL055",
            "method": "GET",
            "uri": "master-data/staff",
            "route_name": "master-data.staff.index",
            "acitve": "1",
            "is_menu": "0",
            "created_at": "2022-5-18 05:04:00",
            "updated_at": "2022-5-18 05:04:00",
            "deleted_at": ""
        },
        {
            "id": "URL056",
            "method": "POST",
            "uri": "master-data/staff",
            "route_name": "master-data.staff.store",
            "acitve": "1",
            "is_menu": "0",
            "created_at": "2022-5-18 05:04:00",
            "updated_at": "2022-5-18 05:04:00",
            "deleted_at": ""
        },
        {
            "id": "URL057",
            "method": "GET",
            "uri": "master-data/staff/create",
            "route_name": "master-data.staff.create",
            "acitve": "1",
            "is_menu": "0",
            "created_at": "2022-5-18 05:04:00",
            "updated_at": "2022-5-18 05:04:00",
            "deleted_at": ""
        },
        {
            "id": "URL058",
            "method": "DELETE",
            "uri": "master-data/staff/{id}",
            "route_name": "master-data.staff.destroy",
            "acitve": "1",
            "is_menu": "0",
            "created_at": "2022-5-18 05:04:00",
            "updated_at": "2022-5-18 05:04:00",
            "deleted_at": ""
        },
        {
            "id": "URL059",
            "method": "PATCH",
            "uri": "master-data/staff/{id}",
            "route_name": "master-data.staff.update",
            "acitve": "1",
            "is_menu": "0",
            "created_at": "2022-5-18 05:04:00",
            "updated_at": "2022-5-18 05:04:00",
            "deleted_at": ""
        },
        {
            "id": "URL060",
            "method": "GET",
            "uri": "master-data/staff/{id}",
            "route_name": "master-data.staff.show",
            "acitve": "1",
            "is_menu": "0",
            "created_at": "2022-5-18 05:04:00",
            "updated_at": "2022-5-18 05:04:00",
            "deleted_at": ""
        },
        {
            "id": "URL061",
            "method": "GET",
            "uri": "master-data/staff/{id}/edit",
            "route_name": "master-data.staff.edit",
            "acitve": "1",
            "is_menu": "0",
            "created_at": "2022-5-18 05:04:00",
            "updated_at": "2022-5-18 05:04:00",
            "deleted_at": ""
        },
        {
            "id": "URL062",
            "method": "GET",
            "uri": "payment-log/deduction",
            "route_name": "payment-log.deduction",
            "acitve": "1",
            "is_menu": "0",
            "created_at": "2022-5-18 05:04:00",
            "updated_at": "2022-5-18 05:04:00",
            "deleted_at": ""
        },
        {
            "id": "URL063",
            "method": "POST",
            "uri": "payment-log/deduction-reverse/{id}",
            "route_name": "payment-log.deduction-reverse",
            "acitve": "1",
            "is_menu": "0",
            "created_at": "2022-5-18 05:04:00",
            "updated_at": "2022-5-18 05:04:00",
            "deleted_at": ""
        },
        {
            "id": "URL064",
            "method": "POST",
            "uri": "payment/deduction",
            "route_name": "payment.deduction.store",
            "acitve": "1",
            "is_menu": "0",
            "created_at": "2022-5-18 05:04:00",
            "updated_at": "2022-5-18 05:04:00",
            "deleted_at": ""
        },
        {
            "id": "URL065",
            "method": "GET",
            "uri": "payment/deduction",
            "route_name": "payment.deduction.index",
            "acitve": "1",
            "is_menu": "0",
            "created_at": "2022-5-18 05:04:00",
            "updated_at": "2022-5-18 05:04:00",
            "deleted_at": ""
        },
        {
            "id": "URL066",
            "method": "PATCH",
            "uri": "payment/deduction/{id}",
            "route_name": "payment.deduction.update",
            "acitve": "1",
            "is_menu": "0",
            "created_at": "2022-5-18 05:04:00",
            "updated_at": "2022-5-18 05:04:00",
            "deleted_at": ""
        },
        {
            "id": "URL067",
            "method": "GET",
            "uri": "payment/deduction/{id}/edit",
            "route_name": "payment.deduction.edit",
            "acitve": "1",
            "is_menu": "0",
            "created_at": "2022-5-18 05:04:00",
            "updated_at": "2022-5-18 05:04:00",
            "deleted_at": ""
        },
        {
            "id": "URL068",
            "method": "GET",
            "uri": "payment/download",
            "route_name": "payment.download",
            "acitve": "1",
            "is_menu": "0",
            "created_at": "2022-5-18 05:04:00",
            "updated_at": "2022-5-18 05:04:00",
            "deleted_at": ""
        },
        {
            "id": "URL069",
            "method": "GET",
            "uri": "payment/export",
            "route_name": "payment.export",
            "acitve": "1",
            "is_menu": "0",
            "created_at": "2022-5-18 05:04:00",
            "updated_at": "2022-5-18 05:04:00",
            "deleted_at": ""
        },
        {
            "id": "URL070",
            "method": "POST",
            "uri": "payment/interest",
            "route_name": "payment.interest.store",
            "acitve": "1",
            "is_menu": "0",
            "created_at": "2022-5-18 05:04:00",
            "updated_at": "2022-5-18 05:04:00",
            "deleted_at": ""
        },
        {
            "id": "URL071",
            "method": "GET",
            "uri": "payment/interest",
            "route_name": "payment.interest.index",
            "acitve": "1",
            "is_menu": "0",
            "created_at": "2022-5-18 05:04:00",
            "updated_at": "2022-5-18 05:04:00",
            "deleted_at": ""
        },
        {
            "id": "URL072",
            "method": "PATCH",
            "uri": "payment/interest/{id}",
            "route_name": "payment.interest.update",
            "acitve": "1",
            "is_menu": "0",
            "created_at": "2022-5-18 05:04:00",
            "updated_at": "2022-5-18 05:04:00",
            "deleted_at": ""
        },
        {
            "id": "URL073",
            "method": "GET",
            "uri": "payment/interest/{id}/edit",
            "route_name": "payment.interest.edit",
            "acitve": "1",
            "is_menu": "0",
            "created_at": "2022-5-18 05:04:00",
            "updated_at": "2022-5-18 05:04:00",
            "deleted_at": ""
        },
        {
            "id": "URL074",
            "method": "GET",
            "uri": "payment/list",
            "route_name": "payment.list.index",
            "acitve": "1",
            "is_menu": "0",
            "created_at": "2022-5-18 05:04:00",
            "updated_at": "2022-5-18 05:04:00",
            "deleted_at": ""
        },
        {
            "id": "URL075",
            "method": "GET",
            "uri": "report-financial/expense",
            "route_name": "report-financial.expense",
            "acitve": "1",
            "is_menu": "0",
            "created_at": "2022-5-18 05:04:00",
            "updated_at": "2022-5-18 05:04:00",
            "deleted_at": ""
        },
        {
            "id": "URL076",
            "method": "GET",
            "uri": "report-financial/revenue-admin-fee",
            "route_name": "report-financial.revenue-admin-fee",
            "acitve": "1",
            "is_menu": "0",
            "created_at": "2022-5-18 05:04:00",
            "updated_at": "2022-5-18 05:04:00",
            "deleted_at": ""
        },
        {
            "id": "URL077",
            "method": "GET",
            "uri": "report-financial/revenue-dividend",
            "route_name": "report-financial.revenue-dividend",
            "acitve": "1",
            "is_menu": "0",
            "created_at": "2022-5-18 05:04:00",
            "updated_at": "2022-5-18 05:04:00",
            "deleted_at": ""
        },
        {
            "id": "URL078",
            "method": "GET",
            "uri": "report-financial/revenue-interest",
            "route_name": "report-financial.revenue-interest",
            "acitve": "1",
            "is_menu": "0",
            "created_at": "2022-5-18 05:04:00",
            "updated_at": "2022-5-18 05:04:00",
            "deleted_at": ""
        },
        {
            "id": "URL079",
            "method": "GET",
            "uri": "report-financial/revenue-interest-export",
            "route_name": "report-financial.revenue-interest-export",
            "acitve": "1",
            "is_menu": "0",
            "created_at": "2022-5-18 05:04:00",
            "updated_at": "2022-5-18 05:04:00",
            "deleted_at": ""
        },
        {
            "id": "URL080",
            "method": "GET",
            "uri": "report-operation/loan",
            "route_name": "report-operation.loan",
            "acitve": "1",
            "is_menu": "0",
            "created_at": "2022-5-18 05:04:00",
            "updated_at": "2022-5-18 05:04:00",
            "deleted_at": ""
        },
        {
            "id": "URL081",
            "method": "GET",
            "uri": "report-operation/loan-export",
            "route_name": "report-operation.loan-export",
            "acitve": "1",
            "is_menu": "0",
            "created_at": "2022-5-18 05:04:00",
            "updated_at": "2022-5-18 05:04:00",
            "deleted_at": ""
        },
        {
            "id": "URL082",
            "method": "GET",
            "uri": "report-staff/revenue-admin-fee",
            "route_name": "report-staff.revenue-admin-fee",
            "acitve": "1",
            "is_menu": "0",
            "created_at": "2022-5-18 05:04:00",
            "updated_at": "2022-5-18 05:04:00",
            "deleted_at": ""
        },
        {
            "id": "URL083",
            "method": "GET",
            "uri": "report-staff/revenue-interest",
            "route_name": "report-staff.revenue-interest",
            "acitve": "1",
            "is_menu": "0",
            "created_at": "2022-5-18 05:04:00",
            "updated_at": "2022-5-18 05:04:00",
            "deleted_at": ""
        },
        {
            "id": "URL084",
            "method": "GET",
            "uri": "report-staff/revenue-interest-export/{id}",
            "route_name": "report-staff.revenue-interest-export",
            "acitve": "1",
            "is_menu": "0",
            "created_at": "2022-5-18 05:04:00",
            "updated_at": "2022-5-18 05:04:00",
            "deleted_at": ""
        },
        {
            "id": "URL085",
            "method": "GET",
            "uri": "report-staff/statistic",
            "route_name": "report-staff.statistic",
            "acitve": "1",
            "is_menu": "0",
            "created_at": "2022-5-18 05:04:00",
            "updated_at": "2022-5-18 05:04:00",
            "deleted_at": ""
        },
        {
            "id": "URL086",
            "method": "GET",
            "uri": "user",
            "route_name": "user.index",
            "acitve": "1",
            "is_menu": "0",
            "created_at": "2022-5-18 05:04:00",
            "updated_at": "2022-5-18 05:04:00",
            "deleted_at": ""
        },
        {
            "id": "URL087",
            "method": "POST",
            "uri": "user",
            "route_name": "user.store",
            "acitve": "1",
            "is_menu": "0",
            "created_at": "2022-5-18 05:04:00",
            "updated_at": "2022-5-18 05:04:00",
            "deleted_at": ""
        },
        {
            "id": "URL088",
            "method": "GET",
            "uri": "user/create",
            "route_name": "user.create",
            "acitve": "1",
            "is_menu": "0",
            "created_at": "2022-5-18 05:04:00",
            "updated_at": "2022-5-18 05:04:00",
            "deleted_at": ""
        },
        {
            "id": "URL089",
            "method": "DELETE",
            "uri": "user/{id}",
            "route_name": "user.destroy",
            "acitve": "1",
            "is_menu": "0",
            "created_at": "2022-5-18 05:04:00",
            "updated_at": "2022-5-18 05:04:00",
            "deleted_at": ""
        },
        {
            "id": "URL090",
            "method": "PATCH",
            "uri": "user/{id}",
            "route_name": "user.update",
            "acitve": "1",
            "is_menu": "0",
            "created_at": "2022-5-18 05:04:00",
            "updated_at": "2022-5-18 05:04:00",
            "deleted_at": ""
        },
        {
            "id": "URL091",
            "method": "GET",
            "uri": "user/{id}",
            "route_name": "user.show",
            "acitve": "1",
            "is_menu": "0",
            "created_at": "2022-5-18 05:04:00",
            "updated_at": "2022-5-18 05:04:00",
            "deleted_at": ""
        },
        {
            "id": "URL092",
            "method": "GET",
            "uri": "user/{id}/edit",
            "route_name": "user.edit",
            "acitve": "1",
            "is_menu": "0",
            "created_at": "2022-5-18 05:04:00",
            "updated_at": "2022-5-18 05:04:00",
            "deleted_at": ""
        },
        {
            "id": "URL093",
            "method": "GET",
            "uri": "profile",
            "route_name": "profile.index",
            "acitve": "1",
            "is_menu": "1",
            "created_at": "",
            "updated_at": "",
            "deleted_at": ""
        },
        {
            "id": "URL094",
            "method": "POST",
            "uri": "profile",
            "route_name": "profile.store",
            "acitve": "1",
            "is_menu": "1",
            "created_at": "",
            "updated_at": "",
            "deleted_at": ""
        },
        {
            "id": "URL095",
            "method": "PATCH",
            "uri": "profile/{id}",
            "route_name": "profile.update",
            "acitve": "1",
            "is_menu": "1",
            "created_at": "",
            "updated_at": "",
            "deleted_at": ""
        },
        {
            "id": "URL096",
            "method": "GET",
            "uri": "profile/{id}/edit",
            "route_name": "profile.edit",
            "acitve": "1",
            "is_menu": "1",
            "created_at": "",
            "updated_at": "",
            "deleted_at": ""
        },
        {
            "id": "URL097",
            "method": "GET",
            "uri": "report-staff/closing",
            "route_name": "report-staff.closing.index",
            "acitve": "1",
            "is_menu": "1",
            "created_at": "",
            "updated_at": "",
            "deleted_at": ""
        },
        {
            "id": "URL098",
            "method": "PATCH",
            "uri": "report-staff/closing/{id}",
            "route_name": "report-staff.closing.update",
            "acitve": "1",
            "is_menu": "0",
            "created_at": "",
            "updated_at": "",
            "deleted_at": ""
        },
        {
            "id": "URL099",
            "method": "GET",
            "uri": "report-staff/closing/{id}",
            "route_name": "report-staff.closing.show",
            "acitve": "1",
            "is_menu": "0",
            "created_at": "",
            "updated_at": "",
            "deleted_at": ""
        },
        {
            "id": "URL100",
            "method": "GET",
            "uri": "report-staff/closing/create",
            "route_name": "report-staff.closing.create",
            "acitve": "1",
            "is_menu": "0",
            "created_at": "",
            "updated_at": "",
            "deleted_at": ""
        },
        {
            "id": "URL101",
            "method": "POST",
            "uri": "report-staff/closing",
            "route_name": "report-staff.closing.store",
            "acitve": "1",
            "is_menu": "0",
            "created_at": "",
            "updated_at": "",
            "deleted_at": ""
        },
        {
            "id": "URL102",
            "method": "GET",
            "uri": "report-staff/closing/{id}/edit",
            "route_name": "report-staff.closing.edit",
            "acitve": "1",
            "is_menu": "0",
            "created_at": "",
            "updated_at": "",
            "deleted_at": ""
        },
        {
            "id": "URL103",
            "method": "GET",
            "uri": "payment-log/transfer/create",
            "route_name": "payment.transfer.create",
            "acitve": "1",
            "is_menu": "1",
            "created_at": "",
            "updated_at": "",
            "deleted_at": ""
        },
        {
            "id": "URL104",
            "method": "GET",
            "uri": "report-staff/closing/create",
            "route_name": "report-staff.closing.create",
            "acitve": "1",
            "is_menu": "1",
            "created_at": "",
            "updated_at": "",
            "deleted_at": ""
        },
        {
            "id": "URL105",
            "method": "POST",
            "uri": "report-staff/closing",
            "route_name": "report-staff.closing.store",
            "acitve": "1",
            "is_menu": "1",
            "created_at": "",
            "updated_at": "",
            "deleted_at": ""
        },
        {
            "id": "URL106",
            "method": "GET",
            "uri": "/payment-log/transfer/create",
            "route_name": "payment-log.transfer.create",
            "acitve": "1",
            "is_menu": "1",
            "created_at": "",
            "updated_at": "",
            "deleted_at": ""
        },
        {
            "id": "URL107",
            "method": "POST",
            "uri": "payment-log/transfer",
            "route_name": "payment-log.transfer.store",
            "acitve": "1",
            "is_menu": "1",
            "created_at": "",
            "updated_at": "",
            "deleted_at": ""
        },
        {
            "id": "URL108",
            "method": "GET",
            "uri": "master-data/calendar/{id}/edit",
            "route_name": "master-data.calendar.edit",
            "acitve": "1",
            "is_menu": "1",
            "created_at": "",
            "updated_at": "",
            "deleted_at": ""
        },
        {
            "id": "URL109",
            "method": "PATCH",
            "uri": "master-data/calendar/{id}",
            "route_name": "master-data.calendar.update",
            "acitve": "1",
            "is_menu": "1",
            "created_at": "",
            "updated_at": "",
            "deleted_at": ""
        },
        {
            "id": "URL110",
            "method": "GET",
            "uri": "master-data/calendar/{id}",
            "route_name": "master-data.calendar.show",
            "acitve": "1",
            "is_menu": "1",
            "created_at": "",
            "updated_at": "",
            "deleted_at": ""
        },
        {
            "id": "URL111",
            "method": "DELETE",
            "uri": "master-data/calendar/{id}",
            "route_name": "master-data.calendar.destroy",
            "acitve": "1",
            "is_menu": "1",
            "created_at": "",
            "updated_at": "",
            "deleted_at": ""
        },
        {
            "id": "URL112",
            "method": "GET",
            "uri": "master-data/calendar/create",
            "route_name": "master-data.calendar.create",
            "acitve": "1",
            "is_menu": "1",
            "created_at": "",
            "updated_at": "",
            "deleted_at": ""
        },
        {
            "id": "URL113",
            "method": "GET",
            "uri": "master-data/calendar",
            "route_name": "master-data.calendar.index",
            "acitve": "1",
            "is_menu": "1",
            "created_at": "",
            "updated_at": "",
            "deleted_at": ""
        },
        {
            "id": "URL114",
            "method": "POST",
            "uri": "master-data/calendar",
            "route_name": "master-data.calendar.store",
            "acitve": "1",
            "is_menu": "1",
            "created_at": "",
            "updated_at": "",
            "deleted_at": ""
        },
        {
            "id": "URL115",
            "method": "GET",
            "uri": "master-data/calendar/download",
            "route_name": "master-data.calendar.download",
            "acitve": "1",
            "is_menu": "1",
            "created_at": "",
            "updated_at": "",
            "deleted_at": ""
        },
        {
            "id": "URL116",
            "method": "GET",
            "uri": "report-financial/revenue-interest-excel",
            "route_name": "report-financial.revenue-interest-excel",
            "acitve": "1",
            "is_menu": "1",
            "created_at": "",
            "updated_at": "",
            "deleted_at": ""
        }
    ]
}